typepyx/__init__.py
typepyx/core.py
typepyx-1.0.4.dist-info/licenses/LICENSE
typepyx-1.0.4.dist-info/METADATA
typepyx-1.0.4.dist-info/WHEEL
typepyx-1.0.4.dist-info/top_level.txt
typepyx-1.0.4.dist-info/RECORD
