Metadata-Version: 2.4
Name: typepyx
Version: 1.0.4
Summary: Custom type system for Python similar to TypeScript
Author: Nambooproo
License: MIT
Requires-Python: >=3.8
License-File: LICENSE
Dynamic: license-file
